tidyfs/__init__.py
tidyfs/cli.py
tidyfs-1.0.0.dist-info/LICENSE
tidyfs-1.0.0.dist-info/METADATA
tidyfs-1.0.0.dist-info/WHEEL
tidyfs-1.0.0.dist-info/entry_points.txt
tidyfs-1.0.0.dist-info/top_level.txt
tidyfs-1.0.0.dist-info/RECORD
