Metadata-Version: 2.2
Name: tidyfs
Version: 1.0.0
Summary: tidyfs is a simple CLI tool to organize files in a directory
Home-page: https://github.com/AnalyticAce/tidyfs
Author: DOSSEH Shalom
Author-email: dossehdosseh14@gmail.com
Classifier: Programming Language :: Python :: 3
Classifier: License :: OSI Approved :: MIT License
Classifier: Operating System :: OS Independent
Requires-Python: >=3.6
License-File: LICENSE
Requires-Dist: typer
Requires-Dist: cron-validator
Dynamic: author
Dynamic: author-email
Dynamic: classifier
Dynamic: description
Dynamic: description-content-type
Dynamic: home-page
Dynamic: requires-dist
Dynamic: requires-python
Dynamic: summary
